setup.py
matvarg_distributions/Binomialdistribution.py
matvarg_distributions/Gaussiandistribution.py
matvarg_distributions/Generaldistribution.py
matvarg_distributions/__init__.py
matvarg_distributions.egg-info/PKG-INFO
matvarg_distributions.egg-info/SOURCES.txt
matvarg_distributions.egg-info/dependency_links.txt
matvarg_distributions.egg-info/not-zip-safe
matvarg_distributions.egg-info/top_level.txt